binarysearchsimulation/Simulation.py
binarysearchsimulation/__init__.py
binarysearchsimulation/command_line.py
binarysearchsimulation/n
binarysearchsimulation/nq
binarysearchsimulation-1.0.2.dist-info/entry_points.txt
binarysearchsimulation-1.0.2.dist-info/LICENSE
binarysearchsimulation-1.0.2.dist-info/WHEEL
binarysearchsimulation-1.0.2.dist-info/METADATA
binarysearchsimulation-1.0.2.dist-info/RECORD
